use_method_tta_ph/__init__.py
use_method_tta_ph/use_method_tta_ph.py
use_method_tta_ph-2.0.0.1.dist-info/LICENSE.txt
use_method_tta_ph-2.0.0.1.dist-info/METADATA
use_method_tta_ph-2.0.0.1.dist-info/WHEEL
use_method_tta_ph-2.0.0.1.dist-info/top_level.txt
use_method_tta_ph-2.0.0.1.dist-info/RECORD
